{
  "pools": [
    {
      "rolls": 1,
      "entries": [
        {
          "type": "minecraft:item",
          "name": "minecraft:leather_leggings",
          "weight": 1
        },
        {
          "type": "minecraft:item",
          "name": "minecraft:iron_leggings",
          "weight": 2
        },
        {
          "type": "minecraft:item",
          "name": "more_stuff:copper_leggings",
          "weight": 2,
          "functions": []
        },
        {
          "type": "minecraft:item",
          "name": "minecraft:chainmail_leggings",
          "weight": 4
        },
        {
          "type": "minecraft:item",
          "name": "minecraft:golden_leggings",
          "weight": 3
        },
        {
          "type": "minecraft:item",
          "name": "minecraft:diamond_leggings",
          "weight": 4
        },
        {
          "type": "minecraft:item",
          "name": "more_stuff:emerald_leggings",
          "weight": 6,
          "functions": []
        }
      ]
    }
  ],
  "random_sequence": "minecraft:armors/end_city/leg_armor"
}