{
  "type": "minecraft:crafting_shapeless",
  "category": "misc",
  "group": "rosarite_ingots",
  "ingredients": [
    {
      "item": "more_stuff:rose_gold_ingot"
    },
    {
      "item": "more_stuff:rose_gold_ingot"
    },
    {
      "item": "more_stuff:rose_gold_ingot"
    },
    {
      "item": "more_stuff:rose_gold_ingot"
    },
    {
      "item": "netherite_scrap"
    },
    {
      "item": "netherite_scrap"
    },
    {
      "item": "netherite_scrap"
    },
    {
      "item": "netherite_scrap"
    }
  ],
  "result": {
    "count": 1,
    "id": "more_stuff:rosarite_ingot"
  }
}